eummy/__init__.py
eummy/eummy.py
eummy-1.0.4.dist-info/licenses/LICENSE
eummy-1.0.4.dist-info/METADATA
eummy-1.0.4.dist-info/WHEEL
eummy-1.0.4.dist-info/entry_points.txt
eummy-1.0.4.dist-info/top_level.txt
eummy-1.0.4.dist-info/RECORD
