Metadata-Version: 2.4
Name: eummy
Version: 1.0.4
Summary: Create color images from Euclid MER stacks
Author-email: Mischa Schirmer <schirmer@mpia.de>
License: GPL-3.0-or-later
Project-URL: Homepage, https://github.com/schirmermischa/eummy
Project-URL: Repository, https://github.com/schirmermischa/eummy
Project-URL: Issues, https://github.com/schirmermischa/eummy/issues
Classifier: Programming Language :: Python :: 3
Classifier: License :: OSI Approved :: GNU General Public License v3 (GPLv3)
Classifier: Operating System :: OS Independent
Classifier: Topic :: Scientific/Engineering :: Astronomy
Classifier: Intended Audience :: Science/Research
Requires-Python: >=3.7
License-File: LICENSE
Requires-Dist: numpy
Requires-Dist: astropy
Requires-Dist: opencv-python
Requires-Dist: tifffile
Requires-Dist: scikit-image
Requires-Dist: scipy
Requires-Dist: matplotlib
Requires-Dist: numexpr
Requires-Dist: psutil
Dynamic: license-file
